cat-readme/__init__.py
cat-readme/cli.py
cat_readme/__init__.py
cat_readme/cli.py
cat_readme-0.1.1.dist-info/METADATA
cat_readme-0.1.1.dist-info/WHEEL
cat_readme-0.1.1.dist-info/entry_points.txt
cat_readme-0.1.1.dist-info/top_level.txt
cat_readme-0.1.1.dist-info/RECORD
