Metadata-Version: 2.1
Name: cat-readme
Version: 0.1.1
Summary: A command-line tool to display markdown files with rich formatting.
Home-page: https://github.com/AnalyticAce/cat-readme
Author: DOSSEH Shalom
Author-email: dossehdosseh14@gmail.com
Classifier: Programming Language :: Python :: 3
Classifier: License :: OSI Approved :: MIT License
Classifier: Operating System :: OS Independent
Requires-Python: >=3.6
Requires-Dist: pathlib
Requires-Dist: rich
Requires-Dist: typer
